thingstuff-0.0.0.dist-info/METADATA
thingstuff-0.0.0.dist-info/WHEEL
thingstuff-0.0.0.dist-info/entry_points.txt
thingstuff-0.0.0.dist-info/licenses/LICENSE
thingstuff/__init__.py
thingstuff/version.py
thingstuff-0.0.0.dist-info/RECORD
